Workbook

Sheet Start Here
A1: Sentinel cash-flow worksheet
A2: Enter only known actuals on Daily Inputs. Blank cells mean unknown—not zero. Formula cells stay blank when required inputs are incomplete.
A4: How to use
A5: 1. Record source-backed daily activity and cash movements in Daily Inputs.
A6: 2. Review Activity Ledger for operating net sales estimate and measured rates.
A7: 3. Review Cash Ledger for NET CASH RECEIVED after cash-paid costs. Processor payouts are bank actuals.
A8: 4. Use Scenario only for the labelled $100/day planning illustration; it is not actual performance.
A9: 5. Review GA4 events in Weekly Review. Never infer purchases from pageviews.
A11: Live ledger summary
A13: Paid orders recorded | B13: ='Activity Ledger'!D20
A14: Gross product sales recorded | B14: ='Activity Ledger'!E20
A15: Operating net sales estimate | B15: ='Activity Ledger'!J20
A16: NET CASH RECEIVED after cash-paid costs | B16: ='Cash Ledger'!G20
A17: Daily input completeness | B17: =IF(COUNTIF('Activity Ledger'!O6:O19,"Complete")=14,"Complete — 14/14 days",IF(COUNTIF('Activity Ledger'!O6:O19,"Complete")=0,"No complete days", "Partial — "&COUNTIF('Activity Ledger'!O6:O19,"Complete")&"/14 days complete")) | C17: Completion is based on all 15 Daily Inputs fields.
A19: Important accounting boundary
A20: Activity Ledger is a recorded-activity view, not a profit statement. Cash Ledger is cash basis: actual processor payouts + affiliate cash paid − refunds paid separately (only when NOT already netted in the payout) − advertising cash paid − other cash expenses paid. If a refund is already netted in the processor payout, enter 0 in Refunds paid separately and do not deduct it again. Do not subtract processor fees or activity/accrual expenses in Cash Ledger.
A23: Input colors
A24: Yellow cells | B24: User-entered assumption or actual input
A25: Blue/gray cells | B25: Formula or recorded total; do not overwrite

Sheet Daily Inputs
A1: Daily inputs — 14-day campaign window
A2: Source actuals only. Keep unknowns blank. If you know that a category had no activity, enter 0; do not use blanks to imply zero. Activity expenses and cash-paid expenses are separate fields.
A5: Date | B5: Website visitors | C5: Checkout clicks | D5: Actual paid orders (sales records) | E5: Actual gross product sales excl. sales taxes | F5: Earned affiliate commissions | G5: Affiliate cash paid | H5: Refunds issued / recorded | I5: Processor fees recorded | J5: Advertising expenses recorded (activity) | K5: Other expenses recorded (activity) | L5: Advertising cash paid | M5: Other cash expenses paid | N5: Actual processor payouts | O5: Refunds paid separately (NOT deducted from payout)
A21: Field guidance
A23: Actual paid orders | B23: Sales records only. Do not substitute checkout clicks or pageviews.
A24: Actual gross product sales | B24: Recorded product sales excluding sales taxes; do not estimate from clicks.
A25: Earned affiliate commissions vs affiliate cash paid | B25: Earned is activity/accrual; cash paid is the money actually received. They are intentionally separate.
A26: Advertising / other expenses | B26: Activity fields are recorded/accrual view only; cash-paid fields are the actual cash basis inputs used by Cash Ledger.
A27: Actual processor payouts | B27: Bank/processor payout actually received. It may already be net of fees and refunds.
A28: Refunds paid separately (NOT deducted from payout) | B28: Cash refund paid outside the processor payout. Enter 0 when the payout already nets the refund; never enter the same refund in both the payout and this field.

Sheet Activity Ledger
A1: Activity Ledger — recorded activity view
A2: Operating net sales estimate = gross product sales + earned affiliate commissions − refunds issued. Activity expenses are recorded/accrual view inputs; this ledger is not a profit statement. Rates appear only with present, positive denominators. Totals are recorded totals and are flagged when partial.
A5: Date | B5: Website visitors | C5: Checkout clicks | D5: Actual paid orders | E5: Gross product sales excl. sales taxes | F5: AOV | G5: Checkout → paid-order rate | H5: Earned affiliate commissions | I5: Refunds issued / recorded | J5: Operating net sales estimate | K5: Processor fees recorded | L5: Advertising expenses recorded (activity) | M5: Other expenses recorded (activity) | N5: Recorded activity contribution estimate (not profit) | O5: Completeness
A6: =IF('Daily Inputs'!A6="","",'Daily Inputs'!A6) | B6: =IF('Daily Inputs'!B6="","",'Daily Inputs'!B6) | C6: =IF('Daily Inputs'!C6="","",'Daily Inputs'!C6) | D6: =IF('Daily Inputs'!D6="","",'Daily Inputs'!D6) | E6: =IF('Daily Inputs'!E6="","",'Daily Inputs'!E6) | F6: =IF(OR(E6="",D6="",D6<=0),"",E6/D6) | G6: =IF(OR(D6="",C6="",C6<=0),"",D6/C6) | H6: =IF('Daily Inputs'!F6="","",'Daily Inputs'!F6) | I6: =IF('Daily Inputs'!H6="","",'Daily Inputs'!H6) | J6: =IF(OR(E6="",H6="",I6=""),"",E6+H6-I6) | K6: =IF('Daily Inputs'!I6="","",'Daily Inputs'!I6) | L6: =IF('Daily Inputs'!J6="","",'Daily Inputs'!J6) | M6: =IF('Daily Inputs'!K6="","",'Daily Inputs'!K6) | N6: =IF(OR(J6="",K6="",L6="",M6=""),"",J6-K6-L6-M6) | O6: =IF(COUNTA('Daily Inputs'!A6:O6)=0,"No entries",IF(COUNTA('Daily Inputs'!A6:O6)=15,"Complete","Partial — "&COUNTA('Daily Inputs'!A6:O6)&" of 15 fields"))
A7: =IF('Daily Inputs'!A7="","",'Daily Inputs'!A7) | B7: =IF('Daily Inputs'!B7="","",'Daily Inputs'!B7) | C7: =IF('Daily Inputs'!C7="","",'Daily Inputs'!C7) | D7: =IF('Daily Inputs'!D7="","",'Daily Inputs'!D7) | E7: =IF('Daily Inputs'!E7="","",'Daily Inputs'!E7) | F7: =IF(OR(E7="",D7="",D7<=0),"",E7/D7) | G7: =IF(OR(D7="",C7="",C7<=0),"",D7/C7) | H7: =IF('Daily Inputs'!F7="","",'Daily Inputs'!F7) | I7: =IF('Daily Inputs'!H7="","",'Daily Inputs'!H7) | J7: =IF(OR(E7="",H7="",I7=""),"",E7+H7-I7) | K7: =IF('Daily Inputs'!I7="","",'Daily Inputs'!I7) | L7: =IF('Daily Inputs'!J7="","",'Daily Inputs'!J7) | M7: =IF('Daily Inputs'!K7="","",'Daily Inputs'!K7) | N7: =IF(OR(J7="",K7="",L7="",M7=""),"",J7-K7-L7-M7) | O7: =IF(COUNTA('Daily Inputs'!A7:O7)=0,"No entries",IF(COUNTA('Daily Inputs'!A7:O7)=15,"Complete","Partial — "&COUNTA('Daily Inputs'!A7:O7)&" of 15 fields"))
A8: =IF('Daily Inputs'!A8="","",'Daily Inputs'!A8) | B8: =IF('Daily Inputs'!B8="","",'Daily Inputs'!B8) | C8: =IF('Daily Inputs'!C8="","",'Daily Inputs'!C8) | D8: =IF('Daily Inputs'!D8="","",'Daily Inputs'!D8) | E8: =IF('Daily Inputs'!E8="","",'Daily Inputs'!E8) | F8: =IF(OR(E8="",D8="",D8<=0),"",E8/D8) | G8: =IF(OR(D8="",C8="",C8<=0),"",D8/C8) | H8: =IF('Daily Inputs'!F8="","",'Daily Inputs'!F8) | I8: =IF('Daily Inputs'!H8="","",'Daily Inputs'!H8) | J8: =IF(OR(E8="",H8="",I8=""),"",E8+H8-I8) | K8: =IF('Daily Inputs'!I8="","",'Daily Inputs'!I8) | L8: =IF('Daily Inputs'!J8="","",'Daily Inputs'!J8) | M8: =IF('Daily Inputs'!K8="","",'Daily Inputs'!K8) | N8: =IF(OR(J8="",K8="",L8="",M8=""),"",J8-K8-L8-M8) | O8: =IF(COUNTA('Daily Inputs'!A8:O8)=0,"No entries",IF(COUNTA('Daily Inputs'!A8:O8)=15,"Complete","Partial — "&COUNTA('Daily Inputs'!A8:O8)&" of 15 fields"))
A9: =IF('Daily Inputs'!A9="","",'Daily Inputs'!A9) | B9: =IF('Daily Inputs'!B9="","",'Daily Inputs'!B9) | C9: =IF('Daily Inputs'!C9="","",'Daily Inputs'!C9) | D9: =IF('Daily Inputs'!D9="","",'Daily Inputs'!D9) | E9: =IF('Daily Inputs'!E9="","",'Daily Inputs'!E9) | F9: =IF(OR(E9="",D9="",D9<=0),"",E9/D9) | G9: =IF(OR(D9="",C9="",C9<=0),"",D9/C9) | H9: =IF('Daily Inputs'!F9="","",'Daily Inputs'!F9) | I9: =IF('Daily Inputs'!H9="","",'Daily Inputs'!H9) | J9: =IF(OR(E9="",H9="",I9=""),"",E9+H9-I9) | K9: =IF('Daily Inputs'!I9="","",'Daily Inputs'!I9) | L9: =IF('Daily Inputs'!J9="","",'Daily Inputs'!J9) | M9: =IF('Daily Inputs'!K9="","",'Daily Inputs'!K9) | N9: =IF(OR(J9="",K9="",L9="",M9=""),"",J9-K9-L9-M9) | O9: =IF(COUNTA('Daily Inputs'!A9:O9)=0,"No entries",IF(COUNTA('Daily Inputs'!A9:O9)=15,"Complete","Partial — "&COUNTA('Daily Inputs'!A9:O9)&" of 15 fields"))
A10: =IF('Daily Inputs'!A10="","",'Daily Inputs'!A10) | B10: =IF('Daily Inputs'!B10="","",'Daily Inputs'!B10) | C10: =IF('Daily Inputs'!C10="","",'Daily Inputs'!C10) | D10: =IF('Daily Inputs'!D10="","",'Daily Inputs'!D10) | E10: =IF('Daily Inputs'!E10="","",'Daily Inputs'!E10) | F10: =IF(OR(E10="",D10="",D10<=0),"",E10/D10) | G10: =IF(OR(D10="",C10="",C10<=0),"",D10/C10) | H10: =IF('Daily Inputs'!F10="","",'Daily Inputs'!F10) | I10: =IF('Daily Inputs'!H10="","",'Daily Inputs'!H10) | J10: =IF(OR(E10="",H10="",I10=""),"",E10+H10-I10) | K10: =IF('Daily Inputs'!I10="","",'Daily Inputs'!I10) | L10: =IF('Daily Inputs'!J10="","",'Daily Inputs'!J10) | M10: =IF('Daily Inputs'!K10="","",'Daily Inputs'!K10) | N10: =IF(OR(J10="",K10="",L10="",M10=""),"",J10-K10-L10-M10) | O10: =IF(COUNTA('Daily Inputs'!A10:O10)=0,"No entries",IF(COUNTA('Daily Inputs'!A10:O10)=15,"Complete","Partial — "&COUNTA('Daily Inputs'!A10:O10)&" of 15 fields"))
A11: =IF('Daily Inputs'!A11="","",'Daily Inputs'!A11) | B11: =IF('Daily Inputs'!B11="","",'Daily Inputs'!B11) | C11: =IF('Daily Inputs'!C11="","",'Daily Inputs'!C11) | D11: =IF('Daily Inputs'!D11="","",'Daily Inputs'!D11) | E11: =IF('Daily Inputs'!E11="","",'Daily Inputs'!E11) | F11: =IF(OR(E11="",D11="",D11<=0),"",E11/D11) | G11: =IF(OR(D11="",C11="",C11<=0),"",D11/C11) | H11: =IF('Daily Inputs'!F11="","",'Daily Inputs'!F11) | I11: =IF('Daily Inputs'!H11="","",'Daily Inputs'!H11) | J11: =IF(OR(E11="",H11="",I11=""),"",E11+H11-I11) | K11: =IF('Daily Inputs'!I11="","",'Daily Inputs'!I11) | L11: =IF('Daily Inputs'!J11="","",'Daily Inputs'!J11) | M11: =IF('Daily Inputs'!K11="","",'Daily Inputs'!K11) | N11: =IF(OR(J11="",K11="",L11="",M11=""),"",J11-K11-L11-M11) | O11: =IF(COUNTA('Daily Inputs'!A11:O11)=0,"No entries",IF(COUNTA('Daily Inputs'!A11:O11)=15,"Complete","Partial — "&COUNTA('Daily Inputs'!A11:O11)&" of 15 fields"))
A12: =IF('Daily Inputs'!A12="","",'Daily Inputs'!A12) | B12: =IF('Daily Inputs'!B12="","",'Daily Inputs'!B12) | C12: =IF('Daily Inputs'!C12="","",'Daily Inputs'!C12) | D12: =IF('Daily Inputs'!D12="","",'Daily Inputs'!D12) | E12: =IF('Daily Inputs'!E12="","",'Daily Inputs'!E12) | F12: =IF(OR(E12="",D12="",D12<=0),"",E12/D12) | G12: =IF(OR(D12="",C12="",C12<=0),"",D12/C12) | H12: =IF('Daily Inputs'!F12="","",'Daily Inputs'!F12) | I12: =IF('Daily Inputs'!H12="","",'Daily Inputs'!H12) | J12: =IF(OR(E12="",H12="",I12=""),"",E12+H12-I12) | K12: =IF('Daily Inputs'!I12="","",'Daily Inputs'!I12) | L12: =IF('Daily Inputs'!J12="","",'Daily Inputs'!J12) | M12: =IF('Daily Inputs'!K12="","",'Daily Inputs'!K12) | N12: =IF(OR(J12="",K12="",L12="",M12=""),"",J12-K12-L12-M12) | O12: =IF(COUNTA('Daily Inputs'!A12:O12)=0,"No entries",IF(COUNTA('Daily Inputs'!A12:O12)=15,"Complete","Partial — "&COUNTA('Daily Inputs'!A12:O12)&" of 15 fields"))
A13: =IF('Daily Inputs'!A13="","",'Daily Inputs'!A13) | B13: =IF('Daily Inputs'!B13="","",'Daily Inputs'!B13) | C13: =IF('Daily Inputs'!C13="","",'Daily Inputs'!C13) | D13: =IF('Daily Inputs'!D13="","",'Daily Inputs'!D13) | E13: =IF('Daily Inputs'!E13="","",'Daily Inputs'!E13) | F13: =IF(OR(E13="",D13="",D13<=0),"",E13/D13) | G13: =IF(OR(D13="",C13="",C13<=0),"",D13/C13) | H13: =IF('Daily Inputs'!F13="","",'Daily Inputs'!F13) | I13: =IF('Daily Inputs'!H13="","",'Daily Inputs'!H13) | J13: =IF(OR(E13="",H13="",I13=""),"",E13+H13-I13) | K13: =IF('Daily Inputs'!I13="","",'Daily Inputs'!I13) | L13: =IF('Daily Inputs'!J13="","",'Daily Inputs'!J13) | M13: =IF('Daily Inputs'!K13="","",'Daily Inputs'!K13) | N13: =IF(OR(J13="",K13="",L13="",M13=""),"",J13-K13-L13-M13) | O13: =IF(COUNTA('Daily Inputs'!A13:O13)=0,"No entries",IF(COUNTA('Daily Inputs'!A13:O13)=15,"Complete","Partial — "&COUNTA('Daily Inputs'!A13:O13)&" of 15 fields"))
A14: =IF('Daily Inputs'!A14="","",'Daily Inputs'!A14) | B14: =IF('Daily Inputs'!B14="","",'Daily Inputs'!B14) | C14: =IF('Daily Inputs'!C14="","",'Daily Inputs'!C14) | D14: =IF('Daily Inputs'!D14="","",'Daily Inputs'!D14) | E14: =IF('Daily Inputs'!E14="","",'Daily Inputs'!E14) | F14: =IF(OR(E14="",D14="",D14<=0),"",E14/D14) | G14: =IF(OR(D14="",C14="",C14<=0),"",D14/C14) | H14: =IF('Daily Inputs'!F14="","",'Daily Inputs'!F14) | I14: =IF('Daily Inputs'!H14="","",'Daily Inputs'!H14) | J14: =IF(OR(E14="",H14="",I14=""),"",E14+H14-I14) | K14: =IF('Daily Inputs'!I14="","",'Daily Inputs'!I14) | L14: =IF('Daily Inputs'!J14="","",'Daily Inputs'!J14) | M14: =IF('Daily Inputs'!K14="","",'Daily Inputs'!K14) | N14: =IF(OR(J14="",K14="",L14="",M14=""),"",J14-K14-L14-M14) | O14: =IF(COUNTA('Daily Inputs'!A14:O14)=0,"No entries",IF(COUNTA('Daily Inputs'!A14:O14)=15,"Complete","Partial — "&COUNTA('Daily Inputs'!A14:O14)&" of 15 fields"))
A15: =IF('Daily Inputs'!A15="","",'Daily Inputs'!A15) | B15: =IF('Daily Inputs'!B15="","",'Daily Inputs'!B15) | C15: =IF('Daily Inputs'!C15="","",'Daily Inputs'!C15) | D15: =IF('Daily Inputs'!D15="","",'Daily Inputs'!D15) | E15: =IF('Daily Inputs'!E15="","",'Daily Inputs'!E15) | F15: =IF(OR(E15="",D15="",D15<=0),"",E15/D15) | G15: =IF(OR(D15="",C15="",C15<=0),"",D15/C15) | H15: =IF('Daily Inputs'!F15="","",'Daily Inputs'!F15) | I15: =IF('Daily Inputs'!H15="","",'Daily Inputs'!H15) | J15: =IF(OR(E15="",H15="",I15=""),"",E15+H15-I15) | K15: =IF('Daily Inputs'!I15="","",'Daily Inputs'!I15) | L15: =IF('Daily Inputs'!J15="","",'Daily Inputs'!J15) | M15: =IF('Daily Inputs'!K15="","",'Daily Inputs'!K15) | N15: =IF(OR(J15="",K15="",L15="",M15=""),"",J15-K15-L15-M15) | O15: =IF(COUNTA('Daily Inputs'!A15:O15)=0,"No entries",IF(COUNTA('Daily Inputs'!A15:O15)=15,"Complete","Partial — "&COUNTA('Daily Inputs'!A15:O15)&" of 15 fields"))
A16: =IF('Daily Inputs'!A16="","",'Daily Inputs'!A16) | B16: =IF('Daily Inputs'!B16="","",'Daily Inputs'!B16) | C16: =IF('Daily Inputs'!C16="","",'Daily Inputs'!C16) | D16: =IF('Daily Inputs'!D16="","",'Daily Inputs'!D16) | E16: =IF('Daily Inputs'!E16="","",'Daily Inputs'!E16) | F16: =IF(OR(E16="",D16="",D16<=0),"",E16/D16) | G16: =IF(OR(D16="",C16="",C16<=0),"",D16/C16) | H16: =IF('Daily Inputs'!F16="","",'Daily Inputs'!F16) | I16: =IF('Daily Inputs'!H16="","",'Daily Inputs'!H16) | J16: =IF(OR(E16="",H16="",I16=""),"",E16+H16-I16) | K16: =IF('Daily Inputs'!I16="","",'Daily Inputs'!I16) | L16: =IF('Daily Inputs'!J16="","",'Daily Inputs'!J16) | M16: =IF('Daily Inputs'!K16="","",'Daily Inputs'!K16) | N16: =IF(OR(J16="",K16="",L16="",M16=""),"",J16-K16-L16-M16) | O16: =IF(COUNTA('Daily Inputs'!A16:O16)=0,"No entries",IF(COUNTA('Daily Inputs'!A16:O16)=15,"Complete","Partial — "&COUNTA('Daily Inputs'!A16:O16)&" of 15 fields"))
A17: =IF('Daily Inputs'!A17="","",'Daily Inputs'!A17) | B17: =IF('Daily Inputs'!B17="","",'Daily Inputs'!B17) | C17: =IF('Daily Inputs'!C17="","",'Daily Inputs'!C17) | D17: =IF('Daily Inputs'!D17="","",'Daily Inputs'!D17) | E17: =IF('Daily Inputs'!E17="","",'Daily Inputs'!E17) | F17: =IF(OR(E17="",D17="",D17<=0),"",E17/D17) | G17: =IF(OR(D17="",C17="",C17<=0),"",D17/C17) | H17: =IF('Daily Inputs'!F17="","",'Daily Inputs'!F17) | I17: =IF('Daily Inputs'!H17="","",'Daily Inputs'!H17) | J17: =IF(OR(E17="",H17="",I17=""),"",E17+H17-I17) | K17: =IF('Daily Inputs'!I17="","",'Daily Inputs'!I17) | L17: =IF('Daily Inputs'!J17="","",'Daily Inputs'!J17) | M17: =IF('Daily Inputs'!K17="","",'Daily Inputs'!K17) | N17: =IF(OR(J17="",K17="",L17="",M17=""),"",J17-K17-L17-M17) | O17: =IF(COUNTA('Daily Inputs'!A17:O17)=0,"No entries",IF(COUNTA('Daily Inputs'!A17:O17)=15,"Complete","Partial — "&COUNTA('Daily Inputs'!A17:O17)&" of 15 fields"))
... A19: =IF('Daily Inputs'!A19="","",'Daily Inputs'!A19) | B19: =IF('Daily Inputs'!B19="","",'Daily Inputs'!B19) | C19: =IF('Daily Inputs'!C19="","",'Daily Inputs'!C19) | D19: =IF('Daily Inputs'!D19="","",'Daily Inputs'!D19) | E19: =IF('Daily Inputs'!E19="","",'Daily Inputs'!E19) | F19: =IF(OR(E19="",D19="",D19<=0),"",E19/D19) | G19: =IF(OR(D19="",C19="",C19<=0),"",D19/C19) | H19: =IF('Daily Inputs'!F19="","",'Daily Inputs'!F19) | I19: =IF('Daily Inputs'!H19="","",'Daily Inputs'!H19) | J19: =IF(OR(E19="",H19="",I19=""),"",E19+H19-I19) | K19: =IF('Daily Inputs'!I19="","",'Daily Inputs'!I19) | L19: =IF('Daily Inputs'!J19="","",'Daily Inputs'!J19) | M19: =IF('Daily Inputs'!K19="","",'Daily Inputs'!K19) | N19: =IF(OR(J19="",K19="",L19="",M19=""),"",J19-K19-L19-M19) | O19: =IF(COUNTA('Daily Inputs'!A19:O19)=0,"No entries",IF(COUNTA('Daily Inputs'!A19:O19)=15,"Complete","Partial — "&COUNTA('Daily Inputs'!A19:O19)&" of 15 fields"))
A20: Recorded totals / rates | B20: =IF(COUNT(B6:B19)=0,"",SUM(B6:B19)) | C20: =IF(COUNT(C6:C19)=0,"",SUM(C6:C19)) | D20: =IF(COUNT(D6:D19)=0,"",SUM(D6:D19)) | E20: =IF(COUNT(E6:E19)=0,"",SUM(E6:E19)) | F20: =IF(AND(COUNT(D6:D19)=14,COUNT(E6:E19)=14,SUM(D6:D19)>0),SUM(E6:E19)/SUM(D6:D19),"") | G20: =IF(AND(COUNT(D6:D19)=14,COUNT(C6:C19)=14,SUM(C6:C19)>0),SUM(D6:D19)/SUM(C6:C19),"") | H20: =IF(COUNT(H6:H19)=0,"",SUM(H6:H19)) | I20: =IF(COUNT(I6:I19)=0,"",SUM(I6:I19)) | J20: =IF(COUNT(J6:J19)=0,"",SUM(J6:J19)) | K20: =IF(COUNT(K6:K19)=0,"",SUM(K6:K19)) | L20: =IF(COUNT(L6:L19)=0,"",SUM(L6:L19)) | M20: =IF(COUNT(M6:M19)=0,"",SUM(M6:M19)) | N20: =IF(COUNT(N6:N19)=0,"",SUM(N6:N19)) | O20: ="See completeness below" -> See completeness below
A21: Completeness | B21: =IF(COUNT(B6:B19)=0,"No entries",IF(COUNT(B6:B19)=14,"Complete — 14/14","Partial — "&COUNT(B6:B19)&"/14")) | C21: =IF(COUNT(C6:C19)=0,"No entries",IF(COUNT(C6:C19)=14,"Complete — 14/14","Partial — "&COUNT(C6:C19)&"/14")) | D21: =IF(COUNT(D6:D19)=0,"No entries",IF(COUNT(D6:D19)=14,"Complete — 14/14","Partial — "&COUNT(D6:D19)&"/14")) | E21: =IF(COUNT(E6:E19)=0,"No entries",IF(COUNT(E6:E19)=14,"Complete — 14/14","Partial — "&COUNT(E6:E19)&"/14")) | F21: =IF(COUNT(F6:F19)=0,"No entries",IF(COUNT(F6:F19)=14,"Complete — 14/14","Partial — "&COUNT(F6:F19)&"/14")) | G21: =IF(COUNT(G6:G19)=0,"No entries",IF(COUNT(G6:G19)=14,"Complete — 14/14","Partial — "&COUNT(G6:G19)&"/14")) | H21: =IF(COUNT(H6:H19)=0,"No entries",IF(COUNT(H6:H19)=14,"Complete — 14/14","Partial — "&COUNT(H6:H19)&"/14")) | I21: =IF(COUNT(I6:I19)=0,"No entries",IF(COUNT(I6:I19)=14,"Complete — 14/14","Partial — "&COUNT(I6:I19)&"/14")) | ... N21: =IF(COUNT(N6:N19)=0,"No entries",IF(COUNT(N6:N19)=14,"Complete — 14/14","Partial — "&COUNT(N6:N19)&"/14")) | O21: =IF(COUNTIF(O6:O19,"Complete")=14,"Complete — 14/14",IF(COUNTIF(O6:O19,"Complete")=0,"No complete days","Partial — "&COUNTIF(O6:O19,"Complete")&"/14"))

Sheet Cash Ledger
A1: Cash Ledger — actual cash view
A2: NET CASH RECEIVED after cash-paid costs = actual processor payouts + affiliate cash paid − refunds paid separately (only when NOT already netted in the payout) − advertising cash paid − other cash expenses paid. Enter 0 for refunds paid separately when the payout already nets the refund. Processor fees and activity/accrual expenses are not deducted here.
A5: Date | B5: Actual processor payouts | C5: Affiliate cash paid | D5: Refunds paid separately (NOT deducted from payout) | E5: Advertising cash paid | F5: Other cash expenses paid | G5: NET CASH RECEIVED after cash-paid costs | H5: Completeness / cash boundary
A6: =IF('Daily Inputs'!A6="","",'Daily Inputs'!A6) | B6: =IF('Daily Inputs'!N6="","",'Daily Inputs'!N6) | C6: =IF('Daily Inputs'!G6="","",'Daily Inputs'!G6) | D6: =IF('Daily Inputs'!O6="","",'Daily Inputs'!O6) | E6: =IF('Daily Inputs'!L6="","",'Daily Inputs'!L6) | F6: =IF('Daily Inputs'!M6="","",'Daily Inputs'!M6) | G6: =IF(OR(B6="",C6="",D6="",E6="",F6=""),"",B6+C6-D6-E6-F6) | H6: =IF(COUNTA('Daily Inputs'!A6:O6)=0,"No entries",IF(AND('Daily Inputs'!N6<>"",'Daily Inputs'!G6<>"",'Daily Inputs'!O6<>"",'Daily Inputs'!L6<>"",'Daily Inputs'!M6<>""),"Cash inputs complete","Cash inputs partial — payout/refund/expense fields required"))
A7: =IF('Daily Inputs'!A7="","",'Daily Inputs'!A7) | B7: =IF('Daily Inputs'!N7="","",'Daily Inputs'!N7) | C7: =IF('Daily Inputs'!G7="","",'Daily Inputs'!G7) | D7: =IF('Daily Inputs'!O7="","",'Daily Inputs'!O7) | E7: =IF('Daily Inputs'!L7="","",'Daily Inputs'!L7) | F7: =IF('Daily Inputs'!M7="","",'Daily Inputs'!M7) | G7: =IF(OR(B7="",C7="",D7="",E7="",F7=""),"",B7+C7-D7-E7-F7) | H7: =IF(COUNTA('Daily Inputs'!A7:O7)=0,"No entries",IF(AND('Daily Inputs'!N7<>"",'Daily Inputs'!G7<>"",'Daily Inputs'!O7<>"",'Daily Inputs'!L7<>"",'Daily Inputs'!M7<>""),"Cash inputs complete","Cash inputs partial — payout/refund/expense fields required"))
A8: =IF('Daily Inputs'!A8="","",'Daily Inputs'!A8) | B8: =IF('Daily Inputs'!N8="","",'Daily Inputs'!N8) | C8: =IF('Daily Inputs'!G8="","",'Daily Inputs'!G8) | D8: =IF('Daily Inputs'!O8="","",'Daily Inputs'!O8) | E8: =IF('Daily Inputs'!L8="","",'Daily Inputs'!L8) | F8: =IF('Daily Inputs'!M8="","",'Daily Inputs'!M8) | G8: =IF(OR(B8="",C8="",D8="",E8="",F8=""),"",B8+C8-D8-E8-F8) | H8: =IF(COUNTA('Daily Inputs'!A8:O8)=0,"No entries",IF(AND('Daily Inputs'!N8<>"",'Daily Inputs'!G8<>"",'Daily Inputs'!O8<>"",'Daily Inputs'!L8<>"",'Daily Inputs'!M8<>""),"Cash inputs complete","Cash inputs partial — payout/refund/expense fields required"))
A9: =IF('Daily Inputs'!A9="","",'Daily Inputs'!A9) | B9: =IF('Daily Inputs'!N9="","",'Daily Inputs'!N9) | C9: =IF('Daily Inputs'!G9="","",'Daily Inputs'!G9) | D9: =IF('Daily Inputs'!O9="","",'Daily Inputs'!O9) | E9: =IF('Daily Inputs'!L9="","",'Daily Inputs'!L9) | F9: =IF('Daily Inputs'!M9="","",'Daily Inputs'!M9) | G9: =IF(OR(B9="",C9="",D9="",E9="",F9=""),"",B9+C9-D9-E9-F9) | H9: =IF(COUNTA('Daily Inputs'!A9:O9)=0,"No entries",IF(AND('Daily Inputs'!N9<>"",'Daily Inputs'!G9<>"",'Daily Inputs'!O9<>"",'Daily Inputs'!L9<>"",'Daily Inputs'!M9<>""),"Cash inputs complete","Cash inputs partial — payout/refund/expense fields required"))
A10: =IF('Daily Inputs'!A10="","",'Daily Inputs'!A10) | B10: =IF('Daily Inputs'!N10="","",'Daily Inputs'!N10) | C10: =IF('Daily Inputs'!G10="","",'Daily Inputs'!G10) | D10: =IF('Daily Inputs'!O10="","",'Daily Inputs'!O10) | E10: =IF('Daily Inputs'!L10="","",'Daily Inputs'!L10) | F10: =IF('Daily Inputs'!M10="","",'Daily Inputs'!M10) | G10: =IF(OR(B10="",C10="",D10="",E10="",F10=""),"",B10+C10-D10-E10-F10) | H10: =IF(COUNTA('Daily Inputs'!A10:O10)=0,"No entries",IF(AND('Daily Inputs'!N10<>"",'Daily Inputs'!G10<>"",'Daily Inputs'!O10<>"",'Daily Inputs'!L10<>"",'Daily Inputs'!M10<>""),"Cash inputs complete","Cash inputs partial — payout/refund/expense fields required"))
A11: =IF('Daily Inputs'!A11="","",'Daily Inputs'!A11) | B11: =IF('Daily Inputs'!N11="","",'Daily Inputs'!N11) | C11: =IF('Daily Inputs'!G11="","",'Daily Inputs'!G11) | D11: =IF('Daily Inputs'!O11="","",'Daily Inputs'!O11) | E11: =IF('Daily Inputs'!L11="","",'Daily Inputs'!L11) | F11: =IF('Daily Inputs'!M11="","",'Daily Inputs'!M11) | G11: =IF(OR(B11="",C11="",D11="",E11="",F11=""),"",B11+C11-D11-E11-F11) | H11: =IF(COUNTA('Daily Inputs'!A11:O11)=0,"No entries",IF(AND('Daily Inputs'!N11<>"",'Daily Inputs'!G11<>"",'Daily Inputs'!O11<>"",'Daily Inputs'!L11<>"",'Daily Inputs'!M11<>""),"Cash inputs complete","Cash inputs partial — payout/refund/expense fields required"))
A12: =IF('Daily Inputs'!A12="","",'Daily Inputs'!A12) | B12: =IF('Daily Inputs'!N12="","",'Daily Inputs'!N12) | C12: =IF('Daily Inputs'!G12="","",'Daily Inputs'!G12) | D12: =IF('Daily Inputs'!O12="","",'Daily Inputs'!O12) | E12: =IF('Daily Inputs'!L12="","",'Daily Inputs'!L12) | F12: =IF('Daily Inputs'!M12="","",'Daily Inputs'!M12) | G12: =IF(OR(B12="",C12="",D12="",E12="",F12=""),"",B12+C12-D12-E12-F12) | H12: =IF(COUNTA('Daily Inputs'!A12:O12)=0,"No entries",IF(AND('Daily Inputs'!N12<>"",'Daily Inputs'!G12<>"",'Daily Inputs'!O12<>"",'Daily Inputs'!L12<>"",'Daily Inputs'!M12<>""),"Cash inputs complete","Cash inputs partial — payout/refund/expense fields required"))
A13: =IF('Daily Inputs'!A13="","",'Daily Inputs'!A13) | B13: =IF('Daily Inputs'!N13="","",'Daily Inputs'!N13) | C13: =IF('Daily Inputs'!G13="","",'Daily Inputs'!G13) | D13: =IF('Daily Inputs'!O13="","",'Daily Inputs'!O13) | E13: =IF('Daily Inputs'!L13="","",'Daily Inputs'!L13) | F13: =IF('Daily Inputs'!M13="","",'Daily Inputs'!M13) | G13: =IF(OR(B13="",C13="",D13="",E13="",F13=""),"",B13+C13-D13-E13-F13) | H13: =IF(COUNTA('Daily Inputs'!A13:O13)=0,"No entries",IF(AND('Daily Inputs'!N13<>"",'Daily Inputs'!G13<>"",'Daily Inputs'!O13<>"",'Daily Inputs'!L13<>"",'Daily Inputs'!M13<>""),"Cash inputs complete","Cash inputs partial — payout/refund/expense fields required"))
A14: =IF('Daily Inputs'!A14="","",'Daily Inputs'!A14) | B14: =IF('Daily Inputs'!N14="","",'Daily Inputs'!N14) | C14: =IF('Daily Inputs'!G14="","",'Daily Inputs'!G14) | D14: =IF('Daily Inputs'!O14="","",'Daily Inputs'!O14) | E14: =IF('Daily Inputs'!L14="","",'Daily Inputs'!L14) | F14: =IF('Daily Inputs'!M14="","",'Daily Inputs'!M14) | G14: =IF(OR(B14="",C14="",D14="",E14="",F14=""),"",B14+C14-D14-E14-F14) | H14: =IF(COUNTA('Daily Inputs'!A14:O14)=0,"No entries",IF(AND('Daily Inputs'!N14<>"",'Daily Inputs'!G14<>"",'Daily Inputs'!O14<>"",'Daily Inputs'!L14<>"",'Daily Inputs'!M14<>""),"Cash inputs complete","Cash inputs partial — payout/refund/expense fields required"))
A15: =IF('Daily Inputs'!A15="","",'Daily Inputs'!A15) | B15: =IF('Daily Inputs'!N15="","",'Daily Inputs'!N15) | C15: =IF('Daily Inputs'!G15="","",'Daily Inputs'!G15) | D15: =IF('Daily Inputs'!O15="","",'Daily Inputs'!O15) | E15: =IF('Daily Inputs'!L15="","",'Daily Inputs'!L15) | F15: =IF('Daily Inputs'!M15="","",'Daily Inputs'!M15) | G15: =IF(OR(B15="",C15="",D15="",E15="",F15=""),"",B15+C15-D15-E15-F15) | H15: =IF(COUNTA('Daily Inputs'!A15:O15)=0,"No entries",IF(AND('Daily Inputs'!N15<>"",'Daily Inputs'!G15<>"",'Daily Inputs'!O15<>"",'Daily Inputs'!L15<>"",'Daily Inputs'!M15<>""),"Cash inputs complete","Cash inputs partial — payout/refund/expense fields required"))
A16: =IF('Daily Inputs'!A16="","",'Daily Inputs'!A16) | B16: =IF('Daily Inputs'!N16="","",'Daily Inputs'!N16) | C16: =IF('Daily Inputs'!G16="","",'Daily Inputs'!G16) | D16: =IF('Daily Inputs'!O16="","",'Daily Inputs'!O16) | E16: =IF('Daily Inputs'!L16="","",'Daily Inputs'!L16) | F16: =IF('Daily Inputs'!M16="","",'Daily Inputs'!M16) | G16: =IF(OR(B16="",C16="",D16="",E16="",F16=""),"",B16+C16-D16-E16-F16) | H16: =IF(COUNTA('Daily Inputs'!A16:O16)=0,"No entries",IF(AND('Daily Inputs'!N16<>"",'Daily Inputs'!G16<>"",'Daily Inputs'!O16<>"",'Daily Inputs'!L16<>"",'Daily Inputs'!M16<>""),"Cash inputs complete","Cash inputs partial — payout/refund/expense fields required"))
A17: =IF('Daily Inputs'!A17="","",'Daily Inputs'!A17) | B17: =IF('Daily Inputs'!N17="","",'Daily Inputs'!N17) | C17: =IF('Daily Inputs'!G17="","",'Daily Inputs'!G17) | D17: =IF('Daily Inputs'!O17="","",'Daily Inputs'!O17) | E17: =IF('Daily Inputs'!L17="","",'Daily Inputs'!L17) | F17: =IF('Daily Inputs'!M17="","",'Daily Inputs'!M17) | G17: =IF(OR(B17="",C17="",D17="",E17="",F17=""),"",B17+C17-D17-E17-F17) | H17: =IF(COUNTA('Daily Inputs'!A17:O17)=0,"No entries",IF(AND('Daily Inputs'!N17<>"",'Daily Inputs'!G17<>"",'Daily Inputs'!O17<>"",'Daily Inputs'!L17<>"",'Daily Inputs'!M17<>""),"Cash inputs complete","Cash inputs partial — payout/refund/expense fields required"))
... A19: =IF('Daily Inputs'!A19="","",'Daily Inputs'!A19) | B19: =IF('Daily Inputs'!N19="","",'Daily Inputs'!N19) | C19: =IF('Daily Inputs'!G19="","",'Daily Inputs'!G19) | D19: =IF('Daily Inputs'!O19="","",'Daily Inputs'!O19) | E19: =IF('Daily Inputs'!L19="","",'Daily Inputs'!L19) | F19: =IF('Daily Inputs'!M19="","",'Daily Inputs'!M19) | G19: =IF(OR(B19="",C19="",D19="",E19="",F19=""),"",B19+C19-D19-E19-F19) | H19: =IF(COUNTA('Daily Inputs'!A19:O19)=0,"No entries",IF(AND('Daily Inputs'!N19<>"",'Daily Inputs'!G19<>"",'Daily Inputs'!O19<>"",'Daily Inputs'!L19<>"",'Daily Inputs'!M19<>""),"Cash inputs complete","Cash inputs partial — payout/refund/expense fields required"))
A20: Recorded totals | B20: =IF(COUNT(B6:B19)=0,"",SUM(B6:B19)) | C20: =IF(COUNT(C6:C19)=0,"",SUM(C6:C19)) | D20: =IF(COUNT(D6:D19)=0,"",SUM(D6:D19)) | E20: =IF(COUNT(E6:E19)=0,"",SUM(E6:E19)) | F20: =IF(COUNT(F6:F19)=0,"",SUM(F6:F19)) | G20: =IF(COUNT(G6:G19)=0,"",SUM(G6:G19))
A21: Completeness | B21: =IF(COUNT(B6:B19)=0,"No entries",IF(COUNT(B6:B19)=14,"Complete — 14/14","Partial — "&COUNT(B6:B19)&"/14")) | C21: =IF(COUNT(C6:C19)=0,"No entries",IF(COUNT(C6:C19)=14,"Complete — 14/14","Partial — "&COUNT(C6:C19)&"/14")) | D21: =IF(COUNT(D6:D19)=0,"No entries",IF(COUNT(D6:D19)=14,"Complete — 14/14","Partial — "&COUNT(D6:D19)&"/14")) | E21: =IF(COUNT(E6:E19)=0,"No entries",IF(COUNT(E6:E19)=14,"Complete — 14/14","Partial — "&COUNT(E6:E19)&"/14")) | F21: =IF(COUNT(F6:F19)=0,"No entries",IF(COUNT(F6:F19)=14,"Complete — 14/14","Partial — "&COUNT(F6:F19)&"/14")) | G21: =IF(COUNT(G6:G19)=0,"No entries",IF(COUNT(G6:G19)=14,"Complete — 14/14","Partial — "&COUNT(G6:G19)&"/14"))

Sheet Scenario
A1: Illustrative $100/day offer scenario
A2: Planning illustration only — not actual results and not linked to the Daily Inputs, Activity Ledger, or Cash Ledger.
A4: Illustrative assumption / output | B4: Value | C4: Type | D4: Interpretation
A5: Target gross sales per day | B5: 100 | C5: Planning input | D5: Illustrative target only; not an observed sales result.
A6: Illustrative price per order | B6: 17.99 | C6: Planning input | D6: Offer price supplied for the scenario; not a recorded transaction price.
A7: Orders required to reach target | B7: =CEILING(B5/B6,1) -> 6 | C7: Formula | D7: CEILING is used so the target is met or exceeded.
A8: Illustrative gross at whole-order count | B8: =B7*B6 -> 107.94 | C8: Formula | D8: Illustrative 6 × $17.99 = $107.94 before taxes, refunds, fees, or expenses.
A10: Optional checkout → paid-order conversion rate assumption | C10: Optional input | D10: Leave blank unless a measured, channel-specific assumption is intentionally used.
A11: Illustrative checkout clicks required at optional checkout → paid-order rate | B11: =IF(OR(B10="",B10<=0),"",B7/B10) | C11: Formula | D11: Blank until the optional rate is entered; this is checkout clicks required, not a website visitor count or actual result.
A13: Guardrail
A14: Do not use this scenario to backfill actual orders, checkout clicks, visitors, conversion, revenue, or cash. The optional rate yields checkout clicks required only; it does not estimate website visitors. Actual paid orders come from sales records; purchases are not attributed from pageviews.

Sheet Weekly Review
A1: Weekly review — measurement and reconciliation
A2: Use source systems to reconcile the worksheet. GA4 events measure intent/leads; they do not replace sales records and pageviews are not purchase attribution.
A5: Review item | B5: Source / GA4 event | C5: Weekly check | D5: Entered result / variance | E5: Owner | F5: Notes
A6: Checkout intent | B6: GA4: product_checkout_click | C6: Reconcile event count to Daily Inputs checkout clicks; inspect tracking gaps.
A7: Lead intent | B7: GA4: lead_form_success | C7: Review successful lead submissions separately from checkout activity.
A8: Paid orders | B8: Sales records | C8: Reconcile paid order count to Actual paid orders; never infer from pageviews.
A9: Gross product sales | B9: Sales records / accounting | C9: Reconcile product sales excluding sales taxes to the recorded sales report.
A10: Processor payouts | B10: Bank / processor statement | C10: Reconcile Actual processor payouts; document payout timing and netting.
A11: Affiliate cash | B11: Affiliate network statement | C11: Reconcile cash paid separately from earned affiliate commissions.
A12: Refunds paid separately | B12: Bank / processor statement | C12: Reconcile cash refunds paid outside processor payouts; enter 0 when the payout already nets the refund.
A14: Attribution rule
A15: Use product_checkout_click for checkout intent and lead_form_success for successful lead submissions. Neither event is a paid order. Pageviews can indicate reach only; do not attribute purchases from pageviews.

Sheet Glossary
A1: Glossary and formula boundaries
A2: Definitions keep recorded activity, accrual-like measures, and bank cash from being mixed.
A4: Term | B4: Definition / boundary
A5: Actual paid orders | B5: Order count from sales records. Checkout clicks and pageviews are not orders.
A6: Actual gross product sales | B6: Recorded product sales excluding sales taxes. Do not estimate from clicks.
A7: Earned affiliate commissions | B7: Commission recognized/earned according to the affiliate source; separate from cash timing.
A8: Affiliate cash paid | B8: Affiliate cash actually received during the day or period.
A9: Refunds issued / recorded | B9: Refund activity recorded in the operating system; distinct from actual cash paid.
A10: Processor fees recorded | B10: Fees recorded as activity/expense; not subtracted in Cash Ledger when processor payouts are already net.
A11: Operating net sales estimate | B11: Gross product sales + earned affiliate commissions − refunds issued. Requires all three inputs.
A12: Actual processor payouts | B12: Cash actually received from the payment processor/bank. Treat as net cash movement from the statement.
A13: Advertising / other expenses | B13: Activity fields are recorded/accrual view inputs. Cash-paid fields are the actual cash basis inputs used by Cash Ledger.
A14: Refunds paid separately (NOT deducted from payout) | B14: Cash refund paid outside the processor payout. Enter 0 when the payout already nets the refund; never enter the same refund in both places.
A15: NET CASH RECEIVED after cash-paid costs | B15: Actual processor payouts + affiliate cash paid − refunds paid separately − advertising cash paid − other cash expenses paid. Do not subtract processor fees or activity/accrual expenses; refunds already netted in payouts must be 0 here.
... A20: GA4 lead_form_success | B20: Weekly review event for successful lead submissions; not a purchase.
